libXML-Parser.so
libEFG-Core.so
efg.cpython-38-i386-linux-gnu.so
efg.libs/libXML-Parser-8009964c.so
efg.libs/libEFG-Core-f8016215.so
efg-0.0.5.dist-info/WHEEL
efg-0.0.5.dist-info/LICENSE
efg-0.0.5.dist-info/RECORD
efg-0.0.5.dist-info/top_level.txt
efg-0.0.5.dist-info/METADATA
