Metadata-Version: 2.1
Name: efg
Version: 0.0.5
Summary: Python bindings of Easy Factor Graph
Author: Andrea Casalino
Author-email: andrecasa91@gmail.com
Keywords: Easy Factor Graph,Bayesian network,Undirect graphical models,graphical models,Random field,Conditional random field
Requires-Python: >=3.7
License-File: LICENSE
